{
  "meta": {
    "last_updated": "2026-02",
    "months": [
      "2026-02"
    ],
    "warehouses": {
      "日本大阪1仓": {
        "platform": "菜鸟",
        "country": "日本",
        "currency": "JPY"
      },
      "英国莱斯特1仓": {
        "platform": "菜鸟",
        "country": "英国",
        "currency": "GBP"
      },
      "美东新泽西2仓": {
        "platform": "菜鸟",
        "country": "美国",
        "currency": "USD"
      },
      "美西洛杉矶5仓": {
        "platform": "菜鸟",
        "country": "美国",
        "currency": "USD"
      },
      "德国法兰克福2仓": {
        "platform": "菜鸟",
        "country": "德国",
        "currency": "EUR"
      },
      "乐仓美国仓": {
        "platform": "乐仓",
        "country": "美国",
        "currency": "USD"
      },
      "乐仓德国仓": {
        "platform": "乐仓",
        "country": "德国",
        "currency": "EUR"
      },
      "乐仓英国仓": {
        "platform": "乐仓",
        "country": "英国",
        "currency": "GBP"
      }
    },
    "sku_mapping_rules": [
      "AC- 开头 → OTHERS",
      "RMA 开头 → OTHERS",
      "US-SHOWROOM / USNY-SHOWROOM → OTHERS",
      "CHAIR-CASTER 开头 → OTHERS",
      "NEXA / NEAT- / NEST- / NUTION 开头 → OTHERS",
      "X2PRO-BLK-CUSTOM → X2",
      "H2PRO-BLK-LR-USED-REST → H2PRO-USED",
      "其他找不到 mapping → OTHERS"
    ],
    "data_source": {
      "菜鸟": "WRF 仓租列表, 计费时间分月, 应收金额",
      "乐仓": "系统费用 sheet, 业务类型=仓储费, 费用发生时间分月, 金额列"
    }
  },
  "storage": {
    "日本大阪1仓": {
      "H1PRO": {
        "180-360天": {
          "2026-02": 4019
        }
      },
      "H2PRO": {
        "180-360天": {
          "2026-02": 44210
        },
        "60-90天": {
          "2026-02": 17475
        },
        "90-120天": {
          "2026-02": 17420
        }
      },
      "H2PRO-FOOTREST": {
        "60-90天": {
          "2026-02": 5571
        },
        "90-120天": {
          "2026-02": 6850
        }
      },
      "H2PRO-USED": {
        "60-90天": {
          "2026-02": 132
        }
      },
      "OTHERS": {
        "120-180天": {
          "2026-02": 1764
        },
        "180-360天": {
          "2026-02": 46663
        },
        "60-90天": {
          "2026-02": 273
        },
        ">360天": {
          "2026-02": 711
        }
      },
      "Q2": {
        "60-90天": {
          "2026-02": 26366
        },
        "90-120天": {
          "2026-02": 33970
        }
      },
      "X2": {
        "180-360天": {
          "2026-02": 12117
        }
      },
      "X2-USED": {
        "120-180天": {
          "2026-02": 1232
        }
      }
    },
    "英国莱斯特1仓": {},
    "美东新泽西2仓": {
      "DESK": {
        "120-180天": {
          "2026-02": 94.64
        }
      },
      "H1CLS-USED": {
        "120-180天": {
          "2026-02": 10.08
        },
        "180-360天": {
          "2026-02": 113.4
        }
      },
      "H1PRO": {
        ">360天": {
          "2026-02": 23.52
        }
      },
      "H1PRO-USED": {
        "120-180天": {
          "2026-02": 112.71
        },
        "180-360天": {
          "2026-02": 726.76
        },
        "60-90天": {
          "2026-02": 16.91
        },
        "90-120天": {
          "2026-02": 15.09
        }
      },
      "H2PRO": {
        "120-180天": {
          "2026-02": 8.12
        }
      },
      "H2PRO-FOOTREST": {
        "60-90天": {
          "2026-02": 2.0
        }
      },
      "H2PRO-USED": {
        "60-90天": {
          "2026-02": 5.28
        },
        "90-120天": {
          "2026-02": 1.08
        }
      },
      "KID": {
        "180-360天": {
          "2026-02": 8.12
        }
      },
      "KID-USED": {
        "180-360天": {
          "2026-02": 24.64
        }
      },
      "OTHERS": {
        "120-180天": {
          "2026-02": 74.73
        },
        "180-360天": {
          "2026-02": 33.79
        },
        "60-90天": {
          "2026-02": 47.18
        },
        "90-120天": {
          "2026-02": 41.38
        },
        ">360天": {
          "2026-02": 22.37
        }
      },
      "OTHERS-USED": {
        "180-360天": {
          "2026-02": 0.56
        }
      },
      "Q1-USED": {
        "120-180天": {
          "2026-02": 4.32
        },
        "180-360天": {
          "2026-02": 16.48
        }
      },
      "Q2": {
        "60-90天": {
          "2026-02": 307.68
        },
        "90-120天": {
          "2026-02": 33.46
        }
      },
      "Q2-USED": {
        "120-180天": {
          "2026-02": 6.79
        },
        "60-90天": {
          "2026-02": 15.5
        },
        "90-120天": {
          "2026-02": 17.48
        }
      },
      "X1-USED": {
        "120-180天": {
          "2026-02": 90.51
        },
        "180-360天": {
          "2026-02": 441.93
        },
        "60-90天": {
          "2026-02": 11.27
        },
        "90-120天": {
          "2026-02": 3.0
        }
      },
      "X2": {
        "60-90天": {
          "2026-02": 88.88
        },
        "90-120天": {
          "2026-02": 13.69
        }
      },
      "X2-USED": {
        "60-90天": {
          "2026-02": 7.2
        }
      }
    },
    "美西洛杉矶5仓": {
      "H2PRO": {
        "60-90天": {
          "2026-02": 1001.85
        }
      },
      "H2PRO-FOOTREST": {
        "60-90天": {
          "2026-02": 79.68
        }
      },
      "KID": {
        ">360天": {
          "2026-02": 13.16
        }
      },
      "OTHERS": {
        "120-180天": {
          "2026-02": 84.61
        },
        "180-360天": {
          "2026-02": 15.49
        },
        "60-90天": {
          "2026-02": 8.19
        },
        ">360天": {
          "2026-02": 241.95
        }
      },
      "Q2": {
        "60-90天": {
          "2026-02": 195.93
        },
        "90-120天": {
          "2026-02": 29.44
        }
      },
      "X2": {
        "120-180天": {
          "2026-02": 9.57
        },
        "60-90天": {
          "2026-02": 221.34
        },
        "90-120天": {
          "2026-02": 40.86
        }
      }
    },
    "德国法兰克福2仓": {
      "H1CLS": {
        "180-360天": {
          "2026-02": 11.76
        }
      },
      "H1PRO": {
        "120-180天": {
          "2026-02": 7.8
        },
        "180-360天": {
          "2026-02": 47.32
        }
      },
      "H1PRO-USED": {
        "120-180天": {
          "2026-02": 49.89
        },
        "180-360天": {
          "2026-02": 26.55
        },
        "60-90天": {
          "2026-02": 12.76
        },
        "90-120天": {
          "2026-02": 8.26
        }
      },
      "H2PRO": {
        "60-90天": {
          "2026-02": 3.42
        }
      },
      "H2PRO-USED": {
        "120-180天": {
          "2026-02": 38.42
        },
        "180-360天": {
          "2026-02": 6.3
        },
        "90-120天": {
          "2026-02": 17.08
        }
      },
      "KID-USED": {
        "60-90天": {
          "2026-02": 0.22
        },
        "90-120天": {
          "2026-02": 4.42
        }
      },
      "OTHERS": {
        "120-180天": {
          "2026-02": 79.38
        },
        "180-360天": {
          "2026-02": 146.42
        },
        "60-90天": {
          "2026-02": 20.38
        },
        "90-120天": {
          "2026-02": 34.23
        },
        ">360天": {
          "2026-02": 129.67
        }
      },
      "Q1": {
        "60-90天": {
          "2026-02": 42.4
        },
        "90-120天": {
          "2026-02": 47.76
        }
      },
      "Q2": {
        "60-90天": {
          "2026-02": 40.5
        }
      },
      "Q2-USED": {
        "120-180天": {
          "2026-02": 0.64
        },
        "60-90天": {
          "2026-02": 5.8
        },
        "90-120天": {
          "2026-02": 4.65
        }
      },
      "X1": {
        ">360天": {
          "2026-02": 64.96
        }
      },
      "X1-USED": {
        "120-180天": {
          "2026-02": 19.04
        }
      },
      "X2-USED": {
        "120-180天": {
          "2026-02": 28.77
        },
        "60-90天": {
          "2026-02": 14.89
        },
        "90-120天": {
          "2026-02": 18.47
        }
      }
    },
    "乐仓美国仓": {
      "H1PRO": {
        "120-180天": {
          "2026-02": 6.04
        }
      },
      "OTHERS": {
        "180-360天": {
          "2026-02": 36.24
        },
        ">360天": {
          "2026-02": 50.6
        }
      }
    },
    "乐仓德国仓": {
      "H1PRO": {
        "120-180天": {
          "2026-02": 5.72
        },
        "30-60天": {
          "2026-02": 1.36
        },
        "60-90天": {
          "2026-02": 5.91
        }
      },
      "OTHERS": {
        "180-360天": {
          "2026-02": 73.93
        },
        ">360天": {
          "2026-02": 19.16
        }
      },
      "X1": {
        "120-180天": {
          "2026-02": 3.88
        },
        "90-120天": {
          "2026-02": 1.02
        }
      }
    },
    "乐仓英国仓": {
      "H1PRO": {
        "120-180天": {
          "2026-02": 4.9
        },
        "90-120天": {
          "2026-02": 2.3
        }
      },
      "H2PRO": {
        "60-90天": {
          "2026-02": 56.67
        },
        "90-120天": {
          "2026-02": 5.07
        }
      },
      "H2PRO-FOOTREST": {
        "60-90天": {
          "2026-02": 28.08
        },
        "90-120天": {
          "2026-02": 1.76
        }
      },
      "OTHERS": {
        "120-180天": {
          "2026-02": 36.66
        },
        "180-360天": {
          "2026-02": 77.81
        },
        "60-90天": {
          "2026-02": 0.25
        }
      },
      "Q2": {
        "60-90天": {
          "2026-02": 231.53
        },
        "90-120天": {
          "2026-02": 37.64
        }
      },
      "X1": {
        "120-180天": {
          "2026-02": 3.46
        },
        "90-120天": {
          "2026-02": 3.35
        }
      }
    }
  }
}